{
  "files": {
    "packages/backend/dist/modules/settlements/settlement.routes.js": {
      "size": 1016,
      "mtime_nanos": 1773294648080153700,
      "mode": 420,
      "is_dir": false
    },
    "packages/backend/dist/modules/transactions/transaction.controller.js": {
      "size": 2661,
      "mtime_nanos": 1773294648105154300,
      "mode": 420,
      "is_dir": false
    },
    "packages/backend/dist/shared/database/prisma.js.map": {
      "size": 462,
      "mtime_nanos": 1773294647834785100,
      "mode": 420,
      "is_dir": false
    },
    "packages/backend/dist/modules/users/user.service.d.ts": {
      "size": 1600,
      "mtime_nanos": 1773052098835710200,
      "mode": 420,
      "is_dir": false
    },
    "packages/backend/dist/shared/services/currency.js.map": {
      "size": 5356,
      "mtime_nanos": 1773294648380619700,
      "mode": 420,
      "is_dir": false
    },
    "packages/backend/dist/middleware/index.d.ts": {
      "size": 254,
      "mtime_nanos": 1773052098795036300,
      "mode": 420,
      "is_dir": false
    },
    "packages/backend/dist/modules/uploads": {
      "size": 0,
      "mtime_nanos": 0,
      "mode": 0,
      "is_dir": true
    },
    "packages/backend/dist/modules/categories/category.routes.js": {
      "size": 840,
      "mtime_nanos": 1773294648180236000,
      "mode": 420,
      "is_dir": false
    },
    "packages/backend/dist/modules/reports/report.controller.js.map": {
      "size": 2820,
      "mtime_nanos": 1773294648286746600,
      "mode": 420,
      "is_dir": false
    },
    "packages/backend/dist/config/env.d.ts.map": {
      "size": 185,
      "mtime_nanos": 1773052098752324800,
      "mode": 420,
      "is_dir": false
    },
    "packages/backend/dist/shared/cache/redis.js": {
      "size": 1591,
      "mtime_nanos": 1773294647893785300,
      "mode": 420,
      "is_dir": false
    },
    "packages/backend/dist/modules/categories/category.controller.d.ts": {
      "size": 532,
      "mtime_nanos": 1773052098918901500,
      "mode": 420,
      "is_dir": false
    },
    "packages/backend/dist/modules/settlements/settlement.routes.js.map": {
      "size": 658,
      "mtime_nanos": 1773294648077153800,
      "mode": 420,
      "is_dir": false
    },
    "packages/backend/dist/graphql/index.js.map": {
      "size": 1593,
      "mtime_nanos": 1773294648344619900,
      "mode": 420,
      "is_dir": false
    },
    "packages/backend/dist/modules/transactions/transaction.controller.d.ts": {
      "size": 756,
      "mtime_nanos": 1773052098899273600,
      "mode": 420,
      "is_dir": false
    },
    "packages/backend/dist/modules/users/user.routes.js.map": {
      "size": 586,
      "mtime_nanos": 1773294647962207800,
      "mode": 420,
      "is_dir": false
    },
    "packages/backend/dist/graphql/index.js": {
      "size": 2447,
      "mtime_nanos": 1773294648347617800,
      "mode": 420,
      "is_dir": false
    },
    "packages/backend/dist/modules/uploads/upload.controller.js.map": {
      "size": 2648,
      "mtime_nanos": 1773294648251746400,
      "mode": 420,
      "is_dir": false
    },
    "packages/backend/dist/modules/budgets/budget.service.d.ts": {
      "size": 2582,
      "mtime_nanos": 1773052098906278800,
      "mode": 420,
      "is_dir": false
    },
    "packages/backend/dist/modules/categories/category.service.d.ts.map": {
      "size": 387,
      "mtime_nanos": 1773052098915898600,
      "mode": 420,
      "is_dir": false
    },
    "packages/backend/dist/modules/auth/auth.routes.js": {
      "size": 1263,
      "mtime_nanos": 1773294647931038600,
      "mode": 420,
      "is_dir": false
    },
    "packages/backend/dist/modules/settlements": {
      "size": 0,
      "mtime_nanos": 0,
      "mode": 0,
      "is_dir": true
    },
    "packages/backend/dist/shared/queue/bullQueue.d.ts.map": {
      "size": 447,
      "mtime_nanos": 1773052098980589000,
      "mode": 420,
      "is_dir": false
    },
    "packages/backend/dist/modules/groups/group.routes.js.map": {
      "size": 908,
      "mtime_nanos": 1773294647996206800,
      "mode": 420,
      "is_dir": false
    },
    "packages/backend/dist/shared/logger.d.ts.map": {
      "size": 178,
      "mtime_nanos": 1773052098758996800,
      "mode": 420,
      "is_dir": false
    },
    "packages/backend/dist/shared/services/ocr.d.ts": {
      "size": 1038,
      "mtime_nanos": 1773052098955812900,
      "mode": 420,
      "is_dir": false
    },
    "packages/backend/dist/config/index.d.ts": {
      "size": 64,
      "mtime_nanos": 1773052098755993900,
      "mode": 420,
      "is_dir": false
    },
    "packages/backend/dist/middleware/index.js": {
      "size": 1143,
      "mtime_nanos": 1773294647882785200,
      "mode": 420,
      "is_dir": false
    },
    "packages/backend/dist/shared/services/s3.d.ts.map": {
      "size": 435,
      "mtime_nanos": 1773052098947819600,
      "mode": 420,
      "is_dir": false
    },
    "packages/backend/dist/modules/budgets/budget.controller.d.ts": {
      "size": 733,
      "mtime_nanos": 1773052098910283600,
      "mode": 420,
      "is_dir": false
    },
    "packages/backend/dist/middleware/rateLimiter.js.map": {
      "size": 702,
      "mtime_nanos": 1773294647868784900,
      "mode": 420,
      "is_dir": false
    },
    "packages/backend/dist/modules/uploads/upload.controller.d.ts.map": {
      "size": 546,
      "mtime_nanos": 1773052098960319800,
      "mode": 420,
      "is_dir": false
    },
    "packages/backend/dist/shared/logger.js": {
      "size": 729,
      "mtime_nanos": 1773294647809374800,
      "mode": 420,
      "is_dir": false
    },
    "packages/backend/dist/modules/budgets/budget.routes.js.map": {
      "size": 701,
      "mtime_nanos": 1773294648146216800,
      "mode": 420,
      "is_dir": false
    },
    "packages/backend/dist/modules/ai/ai.service.js.map": {
      "size": 8444,
      "mtime_nanos": 1773294648189236200,
      "mode": 420,
      "is_dir": false
    },
    "packages/backend/dist/middleware/errorHandler.d.ts": {
      "size": 819,
      "mtime_nanos": 1773052098772007300,
      "mode": 420,
      "is_dir": false
    },
    "packages/backend/dist/graphql/typeDefs.js": {
      "size": 3741,
      "mtime_nanos": 1773294648318107500,
      "mode": 420,
      "is_dir": false
    },
    "packages/backend/dist/modules/groups/group.controller.js": {
      "size": 4092,
      "mtime_nanos": 1773294647989207000,
      "mode": 420,
      "is_dir": false
    },
    "packages/backend/dist/modules/reports/report.routes.js": {
      "size": 732,
      "mtime_nanos": 1773294648300251900,
      "mode": 420,
      "is_dir": false
    },
    "packages/backend/dist/modules/reports/report.service.js.map": {
      "size": 12516,
      "mtime_nanos": 1773294648275743900,
      "mode": 420,
      "is_dir": false
    },
    "packages/backend/dist/modules/uploads/upload.controller.d.ts": {
      "size": 708,
      "mtime_nanos": 1773052098961319600,
      "mode": 420,
      "is_dir": false
    },
    "packages/backend/dist/shared/services/email.js.map": {
      "size": 1806,
      "mtime_nanos": 1773294648398168100,
      "mode": 420,
      "is_dir": false
    },
    "packages/backend/dist/modules/budgets/budget.controller.js": {
      "size": 2431,
      "mtime_nanos": 1773294648139219100,
      "mode": 420,
      "is_dir": false
    },
    "packages/backend/dist/modules/budgets": {
      "size": 0,
      "mtime_nanos": 0,
      "mode": 0,
      "is_dir": true
    },
    "packages/backend/dist/modules/categories/category.routes.js.map": {
      "size": 581,
      "mtime_nanos": 1773294648178235500,
      "mode": 420,
      "is_dir": false
    },
    "packages/backend/dist/middleware/validate.js.map": {
      "size": 541,
      "mtime_nanos": 1773294647856785900,
      "mode": 420,
      "is_dir": false
    },
    "packages/backend/dist/middleware/auth.d.ts": {
      "size": 451,
      "mtime_nanos": 1773052098779018000,
      "mode": 420,
      "is_dir": false
    },
    "packages/backend/dist/modules/ai/ai.service.d.ts": {
      "size": 1285,
      "mtime_nanos": 1773052098931023600,
      "mode": 420,
      "is_dir": false
    },
    "packages/backend/dist/modules/users/user.routes.js": {
      "size": 873,
      "mtime_nanos": 1773294647964206800,
      "mode": 420,
      "is_dir": false
    },
    "packages/backend/dist/modules/users/user.service.js.map": {
      "size": 3670,
      "mtime_nanos": 1773294647937546800,
      "mode": 420,
      "is_dir": false
    },
    "packages/backend/dist/modules/uploads/upload.routes.js.map": {
      "size": 480,
      "mtime_nanos": 1773294648261745800,
      "mode": 420,
      "is_dir": false
    },
    "packages/backend/dist/modules/expenses/expense.controller.js": {
      "size": 2548,
      "mtime_nanos": 1773294648040714900,
      "mode": 420,
      "is_dir": false
    },
    "packages/backend/dist/modules/users/user.controller.js.map": {
      "size": 2044,
      "mtime_nanos": 1773294647951207300,
      "mode": 420,
      "is_dir": false
    },
    "packages/backend/dist/modules/expenses/expense.routes.js.map": {
      "size": 752,
      "mtime_nanos": 1773294648045714400,
      "mode": 420,
      "is_dir": false
    },
    "packages/backend/dist/graphql/resolvers.js.map": {
      "size": 6935,
      "mtime_nanos": 1773294648325113700,
      "mode": 420,
      "is_dir": false
    },
    "packages/backend/dist/modules/ai": { "size": 0, "mtime_nanos": 0, "mode": 0, "is_dir": true },
    "packages/backend/dist/modules/budgets/budget.service.d.ts.map": {
      "size": 811,
      "mtime_nanos": 1773052098905776800,
      "mode": 420,
      "is_dir": false
    },
    "packages/backend/dist/modules/groups/group.controller.d.ts": {
      "size": 1536,
      "mtime_nanos": 1773052098853433000,
      "mode": 420,
      "is_dir": false
    },
    "packages/backend/dist/modules/auth/auth.service.js": {
      "size": 8420,
      "mtime_nanos": 1773294647909020800,
      "mode": 420,
      "is_dir": false
    },
    "packages/backend/dist/modules/groups/group.controller.d.ts.map": {
      "size": 1078,
      "mtime_nanos": 1773052098853433000,
      "mode": 420,
      "is_dir": false
    },
    "packages/backend/dist/middleware": { "size": 0, "mtime_nanos": 0, "mode": 0, "is_dir": true },
    "packages/backend/dist/middleware/errorHandler.d.ts.map": {
      "size": 856,
      "mtime_nanos": 1773052098771008300,
      "mode": 420,
      "is_dir": false
    },
    "packages/backend/dist/modules/expenses/expense.controller.d.ts": {
      "size": 739,
      "mtime_nanos": 1773052098875730300,
      "mode": 420,
      "is_dir": false
    },
    "packages/backend/dist/modules/transactions/transaction.controller.js.map": {
      "size": 2977,
      "mtime_nanos": 1773294648101159700,
      "mode": 420,
      "is_dir": false
    },
    "packages/backend/dist/modules/expenses/expense.routes.js": {
      "size": 1099,
      "mtime_nanos": 1773294648048714500,
      "mode": 420,
      "is_dir": false
    },
    "packages/backend/dist/modules/ai/ai.service.js": {
      "size": 10861,
      "mtime_nanos": 1773294648194235800,
      "mode": 420,
      "is_dir": false
    },
    "packages/backend/dist/modules/settlements/settlement.service.d.ts": {
      "size": 1503,
      "mtime_nanos": 1773052098882237900,
      "mode": 420,
      "is_dir": false
    },
    "packages/backend/dist/middleware/errorHandler.js.map": {
      "size": 3373,
      "mtime_nanos": 1773294647823381700,
      "mode": 420,
      "is_dir": false
    },
    "packages/backend/dist/shared/cache/redis.d.ts": {
      "size": 412,
      "mtime_nanos": 1773052098798541100,
      "mode": 420,
      "is_dir": false
    },
    "packages/backend/dist/shared/database/prisma.d.ts": {
      "size": 70,
      "mtime_nanos": 1773052098774513100,
      "mode": 420,
      "is_dir": false
    },
    "packages/backend/dist/shared/services": {
      "size": 0,
      "mtime_nanos": 0,
      "mode": 0,
      "is_dir": true
    },
    "packages/backend/dist/modules/transactions/transaction.service.js": {
      "size": 8071,
      "mtime_nanos": 1773294648094154200,
      "mode": 420,
      "is_dir": false
    },
    "packages/backend/dist/shared/services/ocr.d.ts.map": {
      "size": 549,
      "mtime_nanos": 1773052098954816300,
      "mode": 420,
      "is_dir": false
    },
    "packages/backend/dist/modules/auth/auth.controller.d.ts.map": {
      "size": 1072,
      "mtime_nanos": 1773052098814565400,
      "mode": 420,
      "is_dir": false
    },
    "packages/backend/dist/modules/settlements/settlement.service.js": {
      "size": 8506,
      "mtime_nanos": 1773294648061153900,
      "mode": 420,
      "is_dir": false
    },
    "packages/backend/dist/modules/ai/ai.controller.js": {
      "size": 1401,
      "mtime_nanos": 1773294648203235700,
      "mode": 420,
      "is_dir": false
    },
    "packages/backend/dist/shared/socket/socketServer.js.map": {
      "size": 2419,
      "mtime_nanos": 1773294648007210100,
      "mode": 420,
      "is_dir": false
    },
    "packages/backend/dist/config/env.js": {
      "size": 2772,
      "mtime_nanos": 1773294647777375000,
      "mode": 420,
      "is_dir": false
    },
    "packages/backend/dist/modules/settlements/settlement.controller.js": {
      "size": 2269,
      "mtime_nanos": 1773294648071155100,
      "mode": 420,
      "is_dir": false
    },
    "packages/backend/dist/modules/categories/category.service.d.ts": {
      "size": 797,
      "mtime_nanos": 1773052098916903000,
      "mode": 420,
      "is_dir": false
    },
    "packages/backend/dist/shared/services/ocr.js": {
      "size": 4928,
      "mtime_nanos": 1773294648242745900,
      "mode": 420,
      "is_dir": false
    },
    "packages/backend/dist/modules/ai/ai.routes.js.map": {
      "size": 422,
      "mtime_nanos": 1773294648210235500,
      "mode": 420,
      "is_dir": false
    },
    "packages/backend/dist/shared/cache": {
      "size": 0,
      "mtime_nanos": 0,
      "mode": 0,
      "is_dir": true
    },
    "packages/backend/dist/graphql/typeDefs.js.map": {
      "size": 351,
      "mtime_nanos": 1773294648316107100,
      "mode": 420,
      "is_dir": false
    },
    "packages/backend/dist/modules/auth/auth.service.js.map": {
      "size": 6539,
      "mtime_nanos": 1773294647902790800,
      "mode": 420,
      "is_dir": false
    },
    "packages/backend/dist/modules/categories/category.controller.d.ts.map": {
      "size": 610,
      "mtime_nanos": 1773052098918901500,
      "mode": 420,
      "is_dir": false
    },
    "packages/backend/dist/modules/categories/category.controller.js": {
      "size": 1767,
      "mtime_nanos": 1773294648170236900,
      "mode": 420,
      "is_dir": false
    },
    "packages/backend/dist/app.js.map": {
      "size": 1986,
      "mtime_nanos": 1773294648304252100,
      "mode": 420,
      "is_dir": false
    },
    "packages/backend/dist/modules/settlements/settlement.controller.js.map": {
      "size": 2465,
      "mtime_nanos": 1773294648067155600,
      "mode": 420,
      "is_dir": false
    },
    "packages/backend/dist/modules/transactions/transaction.routes.js": {
      "size": 1130,
      "mtime_nanos": 1773294648116045000,
      "mode": 420,
      "is_dir": false
    },
    "packages/backend/dist/modules/uploads/upload.controller.js": {
      "size": 3080,
      "mtime_nanos": 1773294648256746200,
      "mode": 420,
      "is_dir": false
    },
    "packages/backend/dist/shared/database/prisma.js": {
      "size": 492,
      "mtime_nanos": 1773294647840785600,
      "mode": 420,
      "is_dir": false
    },
    "packages/backend/dist/shared/services/s3.d.ts": {
      "size": 416,
      "mtime_nanos": 1773052098947819600,
      "mode": 420,
      "is_dir": false
    },
    "packages/backend/dist/modules/expenses/expense.service.js.map": {
      "size": 11770,
      "mtime_nanos": 1773294648023210200,
      "mode": 420,
      "is_dir": false
    },
    "packages/backend/dist/modules/groups/group.service.d.ts.map": {
      "size": 1756,
      "mtime_nanos": 1773052098847929400,
      "mode": 420,
      "is_dir": false
    },
    "packages/backend/dist/shared/socket": {
      "size": 0,
      "mtime_nanos": 0,
      "mode": 0,
      "is_dir": true
    },
    "packages/backend/dist/modules/auth/auth.service.d.ts": {
      "size": 1975,
      "mtime_nanos": 1773052098809049400,
      "mode": 420,
      "is_dir": false
    },
    "packages/backend/dist/app.js": {
      "size": 2864,
      "mtime_nanos": 1773294648310252000,
      "mode": 420,
      "is_dir": false
    },
    "packages/backend/dist/modules/ai/ai.controller.d.ts.map": {
      "size": 500,
      "mtime_nanos": 1773052098933526700,
      "mode": 420,
      "is_dir": false
    },
    "packages/backend/dist/modules/expenses/expense.service.d.ts.map": {
      "size": 527,
      "mtime_nanos": 1773052098871220200,
      "mode": 420,
      "is_dir": false
    },
    "packages/backend/dist/config/env.js.map": {
      "size": 2291,
      "mtime_nanos": 1773294647771378500,
      "mode": 420,
      "is_dir": false
    },
    "packages/backend/dist/modules/auth/auth.controller.js": {
      "size": 3506,
      "mtime_nanos": 1773294647920038000,
      "mode": 420,
      "is_dir": false
    },
    "packages/backend/dist/modules/groups/group.service.d.ts": {
      "size": 2613,
      "mtime_nanos": 1773052098847929400,
      "mode": 420,
      "is_dir": false
    },
    "packages/backend/dist/modules/transactions/transaction.controller.d.ts.map": {
      "size": 820,
      "mtime_nanos": 1773052098898270900,
      "mode": 420,
      "is_dir": false
    },
    "packages/backend/dist/modules/transactions/transaction.service.d.ts": {
      "size": 1521,
      "mtime_nanos": 1773052098895766500,
      "mode": 420,
      "is_dir": false
    },
    "packages/backend/dist/modules/transactions/transaction.service.js.map": {
      "size": 7644,
      "mtime_nanos": 1773294648087154200,
      "mode": 420,
      "is_dir": false
    },
    "packages/backend/dist/modules/groups/group.service.js": {
      "size": 6795,
      "mtime_nanos": 1773294647978207000,
      "mode": 420,
      "is_dir": false
    },
    "packages/backend/dist/modules/budgets/budget.controller.d.ts.map": {
      "size": 799,
      "mtime_nanos": 1773052098910283600,
      "mode": 420,
      "is_dir": false
    },
    "packages/backend/dist/modules/auth/auth.controller.d.ts": {
      "size": 1324,
      "mtime_nanos": 1773052098814565400,
      "mode": 420,
      "is_dir": false
    },
    "packages/backend/dist/modules/users/user.controller.js": {
      "size": 2121,
      "mtime_nanos": 1773294647954206500,
      "mode": 420,
      "is_dir": false
    },
    "packages/backend/dist/modules/auth/auth.controller.js.map": {
      "size": 3443,
      "mtime_nanos": 1773294647917034100,
      "mode": 420,
      "is_dir": false
    },
    "packages/backend/dist/shared/logger.js.map": {
      "size": 454,
      "mtime_nanos": 1773294647797375100,
      "mode": 420,
      "is_dir": false
    },
    "packages/backend/dist/server.js": {
      "size": 1694,
      "mtime_nanos": 1773294648356618600,
      "mode": 420,
      "is_dir": false
    },
    "packages/backend/dist/shared/logger.d.ts": {
      "size": 119,
      "mtime_nanos": 1773052098758996800,
      "mode": 420,
      "is_dir": false
    },
    "packages/backend/dist/modules/groups": {
      "size": 0,
      "mtime_nanos": 0,
      "mode": 0,
      "is_dir": true
    },
    "packages/backend/dist/middleware/index.js.map": {
      "size": 299,
      "mtime_nanos": 1773294647879789800,
      "mode": 420,
      "is_dir": false
    },
    "packages/backend/dist/shared/queue": {
      "size": 0,
      "mtime_nanos": 0,
      "mode": 0,
      "is_dir": true
    },
    "packages/backend/dist/shared/services/currency.js": {
      "size": 6540,
      "mtime_nanos": 1773294648386617800,
      "mode": 420,
      "is_dir": false
    },
    "packages/backend/dist/shared/queue/bullQueue.d.ts": {
      "size": 450,
      "mtime_nanos": 1773052098980589000,
      "mode": 420,
      "is_dir": false
    },
    "packages/backend/dist/server.js.map": {
      "size": 1375,
      "mtime_nanos": 1773294648352618200,
      "mode": 420,
      "is_dir": false
    },
    "packages/backend/dist/shared/socket/socketServer.d.ts.map": {
      "size": 486,
      "mtime_nanos": 1773052098857994200,
      "mode": 420,
      "is_dir": false
    },
    "packages/backend/dist/modules/expenses/expense.service.js": {
      "size": 12998,
      "mtime_nanos": 1773294648029209300,
      "mode": 420,
      "is_dir": false
    },
    "packages/backend/dist/modules/expenses/expense.controller.d.ts.map": {
      "size": 804,
      "mtime_nanos": 1773052098874729200,
      "mode": 420,
      "is_dir": false
    },
    "packages/backend/dist/modules/users/user.service.js": {
      "size": 4824,
      "mtime_nanos": 1773294647945544500,
      "mode": 420,
      "is_dir": false
    },
    "packages/backend/dist/modules/users/user.service.d.ts.map": {
      "size": 1116,
      "mtime_nanos": 1773052098835710200,
      "mode": 420,
      "is_dir": false
    },
    "packages/backend/dist/shared/services/upload.js": {
      "size": 954,
      "mtime_nanos": 1773294648219240000,
      "mode": 420,
      "is_dir": false
    },
    "packages/backend/dist/middleware/auth.js.map": {
      "size": 1418,
      "mtime_nanos": 1773294647847785400,
      "mode": 420,
      "is_dir": false
    },
    "packages/backend/dist/middleware/rateLimiter.d.ts": {
      "size": 216,
      "mtime_nanos": 1773052098792036300,
      "mode": 420,
      "is_dir": false
    },
    "packages/backend/dist/modules/auth": {
      "size": 0,
      "mtime_nanos": 0,
      "mode": 0,
      "is_dir": true
    },
    "packages/backend/dist/modules/groups/group.controller.js.map": {
      "size": 4272,
      "mtime_nanos": 1773294647984207100,
      "mode": 420,
      "is_dir": false
    },
    "packages/backend/dist/shared/services/email.js": {
      "size": 2668,
      "mtime_nanos": 1773294648401168600,
      "mode": 420,
      "is_dir": false
    },
    "packages/backend/dist/modules/settlements/settlement.controller.d.ts.map": {
      "size": 722,
      "mtime_nanos": 1773052098886252900,
      "mode": 420,
      "is_dir": false
    },
    "packages/backend/dist/modules/users/user.controller.d.ts": {
      "size": 815,
      "mtime_nanos": 1773052098839652200,
      "mode": 420,
      "is_dir": false
    },
    "packages/backend/dist/middleware/validate.d.ts.map": {
      "size": 414,
      "mtime_nanos": 1773052098781018100,
      "mode": 420,
      "is_dir": false
    },
    "packages/backend/dist/modules/reports": {
      "size": 0,
      "mtime_nanos": 0,
      "mode": 0,
      "is_dir": true
    },
    "packages/backend/dist/shared": { "size": 0, "mtime_nanos": 0, "mode": 0, "is_dir": true },
    "packages/backend/dist/shared/services/ocr.js.map": {
      "size": 3459,
      "mtime_nanos": 1773294648235746100,
      "mode": 420,
      "is_dir": false
    },
    "packages/backend/dist/modules/reports/report.controller.js": {
      "size": 2815,
      "mtime_nanos": 1773294648292746200,
      "mode": 420,
      "is_dir": false
    },
    "packages/backend/dist/middleware/auth.js": {
      "size": 1900,
      "mtime_nanos": 1773294647850785200,
      "mode": 420,
      "is_dir": false
    },
    "packages/backend/dist/config/index.d.ts.map": {
      "size": 153,
      "mtime_nanos": 1773052098754487600,
      "mode": 420,
      "is_dir": false
    },
    "packages/backend/dist/modules/expenses": {
      "size": 0,
      "mtime_nanos": 0,
      "mode": 0,
      "is_dir": true
    },
    "packages/backend/dist/modules/uploads/upload.routes.js": {
      "size": 728,
      "mtime_nanos": 1773294648264745700,
      "mode": 420,
      "is_dir": false
    },
    "packages/backend/dist/shared/services/email.d.ts.map": {
      "size": 549,
      "mtime_nanos": 1773052098983589500,
      "mode": 420,
      "is_dir": false
    },
    "packages/backend/dist/modules/reports/report.routes.js.map": {
      "size": 504,
      "mtime_nanos": 1773294648297251600,
      "mode": 420,
      "is_dir": false
    },
    "packages/backend/dist/middleware/validate.js": {
      "size": 624,
      "mtime_nanos": 1773294647863785000,
      "mode": 420,
      "is_dir": false
    },
    "packages/backend/dist/modules/categories/category.service.js.map": {
      "size": 3894,
      "mtime_nanos": 1773294648154218800,
      "mode": 420,
      "is_dir": false
    },
    "packages/backend/dist": { "size": 0, "mtime_nanos": 0, "mode": 0, "is_dir": true },
    "packages/backend/dist/modules/reports/report.service.js": {
      "size": 12542,
      "mtime_nanos": 1773294648281746300,
      "mode": 420,
      "is_dir": false
    },
    "packages/backend/dist/graphql": { "size": 0, "mtime_nanos": 0, "mode": 0, "is_dir": true },
    "packages/backend/dist/modules/categories/category.controller.js.map": {
      "size": 1968,
      "mtime_nanos": 1773294648166236400,
      "mode": 420,
      "is_dir": false
    },
    "packages/backend/dist/modules/transactions": {
      "size": 0,
      "mtime_nanos": 0,
      "mode": 0,
      "is_dir": true
    },
    "packages/backend/dist/modules/groups/group.routes.js": {
      "size": 1338,
      "mtime_nanos": 1773294647998206500,
      "mode": 420,
      "is_dir": false
    },
    "packages/backend/dist/modules/users/user.controller.d.ts.map": {
      "size": 643,
      "mtime_nanos": 1773052098839014900,
      "mode": 420,
      "is_dir": false
    },
    "packages/backend/dist/shared/cache/redis.js.map": {
      "size": 1486,
      "mtime_nanos": 1773294647888785200,
      "mode": 420,
      "is_dir": false
    },
    "packages/backend/dist/modules/ai/ai.controller.d.ts": {
      "size": 444,
      "mtime_nanos": 1773052098934531600,
      "mode": 420,
      "is_dir": false
    },
    "packages/backend/dist/modules": { "size": 0, "mtime_nanos": 0, "mode": 0, "is_dir": true },
    "packages/backend/dist/modules/categories/category.service.js": {
      "size": 4589,
      "mtime_nanos": 1773294648161217300,
      "mode": 420,
      "is_dir": false
    },
    "packages/backend/dist/middleware/rateLimiter.d.ts.map": {
      "size": 193,
      "mtime_nanos": 1773052098792036300,
      "mode": 420,
      "is_dir": false
    },
    "packages/backend/dist/shared/socket/socketServer.d.ts": {
      "size": 425,
      "mtime_nanos": 1773052098858949100,
      "mode": 420,
      "is_dir": false
    },
    "packages/backend/dist/graphql/resolvers.js": {
      "size": 7728,
      "mtime_nanos": 1773294648335618000,
      "mode": 420,
      "is_dir": false
    },
    "packages/backend/dist/shared/socket/socketServer.js": {
      "size": 2497,
      "mtime_nanos": 1773294648012206700,
      "mode": 420,
      "is_dir": false
    },
    "packages/backend/dist/modules/ai/ai.controller.js.map": {
      "size": 1465,
      "mtime_nanos": 1773294648200240300,
      "mode": 420,
      "is_dir": false
    },
    "packages/backend/dist/modules/budgets/budget.service.js.map": {
      "size": 5452,
      "mtime_nanos": 1773294648124701400,
      "mode": 420,
      "is_dir": false
    },
    "packages/backend/.turbo/turbo-build.log": {
      "size": 41,
      "mtime_nanos": 1773294648889763200,
      "mode": 420,
      "is_dir": false
    },
    "packages/backend/dist/modules/auth/auth.routes.js.map": {
      "size": 871,
      "mtime_nanos": 1773294647929041000,
      "mode": 420,
      "is_dir": false
    },
    "packages/backend/dist/shared/queue/bullQueue.js": {
      "size": 1193,
      "mtime_nanos": 1773294648370618000,
      "mode": 420,
      "is_dir": false
    },
    "packages/backend/dist/middleware/errorHandler.js": {
      "size": 3643,
      "mtime_nanos": 1773294647829378700,
      "mode": 420,
      "is_dir": false
    },
    "packages/backend/dist/shared/database/prisma.d.ts.map": {
      "size": 157,
      "mtime_nanos": 1773052098774513100,
      "mode": 420,
      "is_dir": false
    },
    "packages/backend/dist/modules/auth/auth.service.d.ts.map": {
      "size": 927,
      "mtime_nanos": 1773052098808049400,
      "mode": 420,
      "is_dir": false
    },
    "packages/backend/dist/shared/queue/bullQueue.js.map": {
      "size": 1155,
      "mtime_nanos": 1773294648362619300,
      "mode": 420,
      "is_dir": false
    },
    "packages/backend/dist/modules/budgets/budget.service.js": {
      "size": 6104,
      "mtime_nanos": 1773294648128701100,
      "mode": 420,
      "is_dir": false
    },
    "packages/backend/dist/modules/settlements/settlement.controller.d.ts": {
      "size": 663,
      "mtime_nanos": 1773052098886252900,
      "mode": 420,
      "is_dir": false
    },
    "packages/backend/dist/middleware/validate.d.ts": {
      "size": 510,
      "mtime_nanos": 1773052098781018100,
      "mode": 420,
      "is_dir": false
    },
    "packages/backend/dist/modules/transactions/transaction.service.d.ts.map": {
      "size": 519,
      "mtime_nanos": 1773052098895766500,
      "mode": 420,
      "is_dir": false
    },
    "packages/backend/dist/shared/services/s3.js": {
      "size": 1742,
      "mtime_nanos": 1773294648229240400,
      "mode": 420,
      "is_dir": false
    },
    "packages/backend/dist/shared/services/s3.js.map": {
      "size": 1479,
      "mtime_nanos": 1773294648225240000,
      "mode": 420,
      "is_dir": false
    },
    "packages/backend/dist/server.d.ts.map": {
      "size": 106,
      "mtime_nanos": 1773052098973350400,
      "mode": 420,
      "is_dir": false
    },
    "packages/backend/dist/shared/services/upload.js.map": {
      "size": 805,
      "mtime_nanos": 1773294648216236400,
      "mode": 420,
      "is_dir": false
    },
    "packages/backend/dist/modules/transactions/transaction.routes.js.map": {
      "size": 762,
      "mtime_nanos": 1773294648112043900,
      "mode": 420,
      "is_dir": false
    },
    "packages/backend/dist/config/index.js": {
      "size": 263,
      "mtime_nanos": 1773294647790374700,
      "mode": 420,
      "is_dir": false
    },
    "packages/backend/dist/modules/budgets/budget.routes.js": {
      "size": 984,
      "mtime_nanos": 1773294648148216500,
      "mode": 420,
      "is_dir": false
    },
    "packages/backend/dist/config/env.d.ts": {
      "size": 1357,
      "mtime_nanos": 1773052098752324800,
      "mode": 420,
      "is_dir": false
    },
    "packages/backend/dist/middleware/auth.d.ts.map": {
      "size": 404,
      "mtime_nanos": 1773052098778018100,
      "mode": 420,
      "is_dir": false
    },
    "packages/backend/dist/server.d.ts": {
      "size": 47,
      "mtime_nanos": 1773052098973350400,
      "mode": 420,
      "is_dir": false
    },
    "packages/backend/dist/config/index.js.map": {
      "size": 148,
      "mtime_nanos": 1773294647785375300,
      "mode": 420,
      "is_dir": false
    },
    "packages/backend/dist/shared/cache/redis.d.ts.map": {
      "size": 497,
      "mtime_nanos": 1773052098798541100,
      "mode": 420,
      "is_dir": false
    },
    "packages/backend/dist/shared/services/email.d.ts": {
      "size": 489,
      "mtime_nanos": 1773052098983589500,
      "mode": 420,
      "is_dir": false
    },
    "packages/backend/dist/config": { "size": 0, "mtime_nanos": 0, "mode": 0, "is_dir": true },
    "packages/backend/dist/middleware/index.d.ts.map": {
      "size": 319,
      "mtime_nanos": 1773052098794038900,
      "mode": 420,
      "is_dir": false
    },
    "packages/backend/dist/modules/groups/group.service.js.map": {
      "size": 5523,
      "mtime_nanos": 1773294647973207900,
      "mode": 420,
      "is_dir": false
    },
    "packages/backend/dist/modules/expenses/expense.service.d.ts": {
      "size": 2215,
      "mtime_nanos": 1773052098871220200,
      "mode": 420,
      "is_dir": false
    },
    "packages/backend/dist/modules/settlements/settlement.service.d.ts.map": {
      "size": 437,
      "mtime_nanos": 1773052098882237900,
      "mode": 420,
      "is_dir": false
    },
    "packages/backend/dist/shared/database": {
      "size": 0,
      "mtime_nanos": 0,
      "mode": 0,
      "is_dir": true
    },
    "packages/backend/dist/modules/budgets/budget.controller.js.map": {
      "size": 2841,
      "mtime_nanos": 1773294648134211600,
      "mode": 420,
      "is_dir": false
    },
    "packages/backend/dist/modules/categories": {
      "size": 0,
      "mtime_nanos": 0,
      "mode": 0,
      "is_dir": true
    },
    "packages/backend/dist/modules/settlements/settlement.service.js.map": {
      "size": 7610,
      "mtime_nanos": 1773294648056153900,
      "mode": 420,
      "is_dir": false
    },
    "packages/backend/dist/modules/ai/ai.routes.js": {
      "size": 595,
      "mtime_nanos": 1773294648212235700,
      "mode": 420,
      "is_dir": false
    },
    "packages/backend/dist/modules/expenses/expense.controller.js.map": {
      "size": 2960,
      "mtime_nanos": 1773294648034714200,
      "mode": 420,
      "is_dir": false
    },
    "packages/backend/dist/middleware/rateLimiter.js": {
      "size": 1159,
      "mtime_nanos": 1773294647870785800,
      "mode": 420,
      "is_dir": false
    },
    "packages/backend/dist/modules/users": {
      "size": 0,
      "mtime_nanos": 0,
      "mode": 0,
      "is_dir": true
    },
    "packages/backend/dist/modules/ai/ai.service.d.ts.map": {
      "size": 357,
      "mtime_nanos": 1773052098931023600,
      "mode": 420,
      "is_dir": false
    }
  },
  "order": [
    "packages/backend/.turbo/turbo-build.log",
    "packages/backend/dist",
    "packages/backend/dist/app.js",
    "packages/backend/dist/app.js.map",
    "packages/backend/dist/config",
    "packages/backend/dist/config/env.d.ts",
    "packages/backend/dist/config/env.d.ts.map",
    "packages/backend/dist/config/env.js",
    "packages/backend/dist/config/env.js.map",
    "packages/backend/dist/config/index.d.ts",
    "packages/backend/dist/config/index.d.ts.map",
    "packages/backend/dist/config/index.js",
    "packages/backend/dist/config/index.js.map",
    "packages/backend/dist/graphql",
    "packages/backend/dist/graphql/index.js",
    "packages/backend/dist/graphql/index.js.map",
    "packages/backend/dist/graphql/resolvers.js",
    "packages/backend/dist/graphql/resolvers.js.map",
    "packages/backend/dist/graphql/typeDefs.js",
    "packages/backend/dist/graphql/typeDefs.js.map",
    "packages/backend/dist/middleware",
    "packages/backend/dist/middleware/auth.d.ts",
    "packages/backend/dist/middleware/auth.d.ts.map",
    "packages/backend/dist/middleware/auth.js",
    "packages/backend/dist/middleware/auth.js.map",
    "packages/backend/dist/middleware/errorHandler.d.ts",
    "packages/backend/dist/middleware/errorHandler.d.ts.map",
    "packages/backend/dist/middleware/errorHandler.js",
    "packages/backend/dist/middleware/errorHandler.js.map",
    "packages/backend/dist/middleware/index.d.ts",
    "packages/backend/dist/middleware/index.d.ts.map",
    "packages/backend/dist/middleware/index.js",
    "packages/backend/dist/middleware/index.js.map",
    "packages/backend/dist/middleware/rateLimiter.d.ts",
    "packages/backend/dist/middleware/rateLimiter.d.ts.map",
    "packages/backend/dist/middleware/rateLimiter.js",
    "packages/backend/dist/middleware/rateLimiter.js.map",
    "packages/backend/dist/middleware/validate.d.ts",
    "packages/backend/dist/middleware/validate.d.ts.map",
    "packages/backend/dist/middleware/validate.js",
    "packages/backend/dist/middleware/validate.js.map",
    "packages/backend/dist/modules",
    "packages/backend/dist/modules/ai",
    "packages/backend/dist/modules/ai/ai.controller.d.ts",
    "packages/backend/dist/modules/ai/ai.controller.d.ts.map",
    "packages/backend/dist/modules/ai/ai.controller.js",
    "packages/backend/dist/modules/ai/ai.controller.js.map",
    "packages/backend/dist/modules/ai/ai.routes.js",
    "packages/backend/dist/modules/ai/ai.routes.js.map",
    "packages/backend/dist/modules/ai/ai.service.d.ts",
    "packages/backend/dist/modules/ai/ai.service.d.ts.map",
    "packages/backend/dist/modules/ai/ai.service.js",
    "packages/backend/dist/modules/ai/ai.service.js.map",
    "packages/backend/dist/modules/auth",
    "packages/backend/dist/modules/auth/auth.controller.d.ts",
    "packages/backend/dist/modules/auth/auth.controller.d.ts.map",
    "packages/backend/dist/modules/auth/auth.controller.js",
    "packages/backend/dist/modules/auth/auth.controller.js.map",
    "packages/backend/dist/modules/auth/auth.routes.js",
    "packages/backend/dist/modules/auth/auth.routes.js.map",
    "packages/backend/dist/modules/auth/auth.service.d.ts",
    "packages/backend/dist/modules/auth/auth.service.d.ts.map",
    "packages/backend/dist/modules/auth/auth.service.js",
    "packages/backend/dist/modules/auth/auth.service.js.map",
    "packages/backend/dist/modules/budgets",
    "packages/backend/dist/modules/budgets/budget.controller.d.ts",
    "packages/backend/dist/modules/budgets/budget.controller.d.ts.map",
    "packages/backend/dist/modules/budgets/budget.controller.js",
    "packages/backend/dist/modules/budgets/budget.controller.js.map",
    "packages/backend/dist/modules/budgets/budget.routes.js",
    "packages/backend/dist/modules/budgets/budget.routes.js.map",
    "packages/backend/dist/modules/budgets/budget.service.d.ts",
    "packages/backend/dist/modules/budgets/budget.service.d.ts.map",
    "packages/backend/dist/modules/budgets/budget.service.js",
    "packages/backend/dist/modules/budgets/budget.service.js.map",
    "packages/backend/dist/modules/categories",
    "packages/backend/dist/modules/categories/category.controller.d.ts",
    "packages/backend/dist/modules/categories/category.controller.d.ts.map",
    "packages/backend/dist/modules/categories/category.controller.js",
    "packages/backend/dist/modules/categories/category.controller.js.map",
    "packages/backend/dist/modules/categories/category.routes.js",
    "packages/backend/dist/modules/categories/category.routes.js.map",
    "packages/backend/dist/modules/categories/category.service.d.ts",
    "packages/backend/dist/modules/categories/category.service.d.ts.map",
    "packages/backend/dist/modules/categories/category.service.js",
    "packages/backend/dist/modules/categories/category.service.js.map",
    "packages/backend/dist/modules/expenses",
    "packages/backend/dist/modules/expenses/expense.controller.d.ts",
    "packages/backend/dist/modules/expenses/expense.controller.d.ts.map",
    "packages/backend/dist/modules/expenses/expense.controller.js",
    "packages/backend/dist/modules/expenses/expense.controller.js.map",
    "packages/backend/dist/modules/expenses/expense.routes.js",
    "packages/backend/dist/modules/expenses/expense.routes.js.map",
    "packages/backend/dist/modules/expenses/expense.service.d.ts",
    "packages/backend/dist/modules/expenses/expense.service.d.ts.map",
    "packages/backend/dist/modules/expenses/expense.service.js",
    "packages/backend/dist/modules/expenses/expense.service.js.map",
    "packages/backend/dist/modules/groups",
    "packages/backend/dist/modules/groups/group.controller.d.ts",
    "packages/backend/dist/modules/groups/group.controller.d.ts.map",
    "packages/backend/dist/modules/groups/group.controller.js",
    "packages/backend/dist/modules/groups/group.controller.js.map",
    "packages/backend/dist/modules/groups/group.routes.js",
    "packages/backend/dist/modules/groups/group.routes.js.map",
    "packages/backend/dist/modules/groups/group.service.d.ts",
    "packages/backend/dist/modules/groups/group.service.d.ts.map",
    "packages/backend/dist/modules/groups/group.service.js",
    "packages/backend/dist/modules/groups/group.service.js.map",
    "packages/backend/dist/modules/reports",
    "packages/backend/dist/modules/reports/report.controller.js",
    "packages/backend/dist/modules/reports/report.controller.js.map",
    "packages/backend/dist/modules/reports/report.routes.js",
    "packages/backend/dist/modules/reports/report.routes.js.map",
    "packages/backend/dist/modules/reports/report.service.js",
    "packages/backend/dist/modules/reports/report.service.js.map",
    "packages/backend/dist/modules/settlements",
    "packages/backend/dist/modules/settlements/settlement.controller.d.ts",
    "packages/backend/dist/modules/settlements/settlement.controller.d.ts.map",
    "packages/backend/dist/modules/settlements/settlement.controller.js",
    "packages/backend/dist/modules/settlements/settlement.controller.js.map",
    "packages/backend/dist/modules/settlements/settlement.routes.js",
    "packages/backend/dist/modules/settlements/settlement.routes.js.map",
    "packages/backend/dist/modules/settlements/settlement.service.d.ts",
    "packages/backend/dist/modules/settlements/settlement.service.d.ts.map",
    "packages/backend/dist/modules/settlements/settlement.service.js",
    "packages/backend/dist/modules/settlements/settlement.service.js.map",
    "packages/backend/dist/modules/transactions",
    "packages/backend/dist/modules/transactions/transaction.controller.d.ts",
    "packages/backend/dist/modules/transactions/transaction.controller.d.ts.map",
    "packages/backend/dist/modules/transactions/transaction.controller.js",
    "packages/backend/dist/modules/transactions/transaction.controller.js.map",
    "packages/backend/dist/modules/transactions/transaction.routes.js",
    "packages/backend/dist/modules/transactions/transaction.routes.js.map",
    "packages/backend/dist/modules/transactions/transaction.service.d.ts",
    "packages/backend/dist/modules/transactions/transaction.service.d.ts.map",
    "packages/backend/dist/modules/transactions/transaction.service.js",
    "packages/backend/dist/modules/transactions/transaction.service.js.map",
    "packages/backend/dist/modules/uploads",
    "packages/backend/dist/modules/uploads/upload.controller.d.ts",
    "packages/backend/dist/modules/uploads/upload.controller.d.ts.map",
    "packages/backend/dist/modules/uploads/upload.controller.js",
    "packages/backend/dist/modules/uploads/upload.controller.js.map",
    "packages/backend/dist/modules/uploads/upload.routes.js",
    "packages/backend/dist/modules/uploads/upload.routes.js.map",
    "packages/backend/dist/modules/users",
    "packages/backend/dist/modules/users/user.controller.d.ts",
    "packages/backend/dist/modules/users/user.controller.d.ts.map",
    "packages/backend/dist/modules/users/user.controller.js",
    "packages/backend/dist/modules/users/user.controller.js.map",
    "packages/backend/dist/modules/users/user.routes.js",
    "packages/backend/dist/modules/users/user.routes.js.map",
    "packages/backend/dist/modules/users/user.service.d.ts",
    "packages/backend/dist/modules/users/user.service.d.ts.map",
    "packages/backend/dist/modules/users/user.service.js",
    "packages/backend/dist/modules/users/user.service.js.map",
    "packages/backend/dist/server.d.ts",
    "packages/backend/dist/server.d.ts.map",
    "packages/backend/dist/server.js",
    "packages/backend/dist/server.js.map",
    "packages/backend/dist/shared",
    "packages/backend/dist/shared/cache",
    "packages/backend/dist/shared/cache/redis.d.ts",
    "packages/backend/dist/shared/cache/redis.d.ts.map",
    "packages/backend/dist/shared/cache/redis.js",
    "packages/backend/dist/shared/cache/redis.js.map",
    "packages/backend/dist/shared/database",
    "packages/backend/dist/shared/database/prisma.d.ts",
    "packages/backend/dist/shared/database/prisma.d.ts.map",
    "packages/backend/dist/shared/database/prisma.js",
    "packages/backend/dist/shared/database/prisma.js.map",
    "packages/backend/dist/shared/logger.d.ts",
    "packages/backend/dist/shared/logger.d.ts.map",
    "packages/backend/dist/shared/logger.js",
    "packages/backend/dist/shared/logger.js.map",
    "packages/backend/dist/shared/queue",
    "packages/backend/dist/shared/queue/bullQueue.d.ts",
    "packages/backend/dist/shared/queue/bullQueue.d.ts.map",
    "packages/backend/dist/shared/queue/bullQueue.js",
    "packages/backend/dist/shared/queue/bullQueue.js.map",
    "packages/backend/dist/shared/services",
    "packages/backend/dist/shared/services/currency.js",
    "packages/backend/dist/shared/services/currency.js.map",
    "packages/backend/dist/shared/services/email.d.ts",
    "packages/backend/dist/shared/services/email.d.ts.map",
    "packages/backend/dist/shared/services/email.js",
    "packages/backend/dist/shared/services/email.js.map",
    "packages/backend/dist/shared/services/ocr.d.ts",
    "packages/backend/dist/shared/services/ocr.d.ts.map",
    "packages/backend/dist/shared/services/ocr.js",
    "packages/backend/dist/shared/services/ocr.js.map",
    "packages/backend/dist/shared/services/s3.d.ts",
    "packages/backend/dist/shared/services/s3.d.ts.map",
    "packages/backend/dist/shared/services/s3.js",
    "packages/backend/dist/shared/services/s3.js.map",
    "packages/backend/dist/shared/services/upload.js",
    "packages/backend/dist/shared/services/upload.js.map",
    "packages/backend/dist/shared/socket",
    "packages/backend/dist/shared/socket/socketServer.d.ts",
    "packages/backend/dist/shared/socket/socketServer.d.ts.map",
    "packages/backend/dist/shared/socket/socketServer.js",
    "packages/backend/dist/shared/socket/socketServer.js.map"
  ]
}
